{"Unit Tests":{"coverage":{"/Users/ajrkerr/Development/roo/lib/roo.rb":[1,null,1,null,1,0,null,0,0,null,0,0,null,0,0,null,0,0,null,0,null,null,null,1,1,null,1,1,1,1,1,1,1,null],"/Users/ajrkerr/Development/roo/lib/roo/base.rb":[null,null,1,1,null,1,1,0,null,null,1,1,null,null,null,null,null,null,1,1,null,1,null,1,null,null,1,null,null,1,null,1,0,0,null,0,0,0,null,0,0,0,0,null,0,0,null,null,null,null,1,0,0,null,0,0,0,0,0,null,null,null,1,0,null,null,null,1,0,null,null,null,null,1,0,0,0,0,null,0,0,null,0,0,0,0,null,null,null,0,null,0,0,null,null,null,1,0,0,0,0,null,0,0,null,0,0,0,0,0,0,null,null,null,1,0,0,0,0,null,0,0,null,0,0,0,0,0,0,null,null,null,1,0,0,0,0,null,0,0,null,0,0,0,0,0,0,null,null,null,null,null,1,0,0,0,null,0,0,0,0,0,0,null,0,0,0,0,0,null,0,null,null,null,null,0,null,null,null,1,0,0,0,0,null,0,null,0,0,0,0,null,null,null,null,1,0,null,0,0,null,0,0,0,null,null,null,null,null,null,null,1,0,null,0,0,0,0,null,null,null,null,null,1,0,0,0,0,null,null,null,null,null,1,0,0,null,0,0,0,0,null,null,null,null,null,1,0,0,0,0,0,0,null,0,null,null,0,0,null,null,null,1,0,0,0,null,null,null,1,0,0,0,0,0,0,null,null,null,null,1,0,0,null,null,0,0,0,0,0,0,null,0,0,0,0,null,0,0,null,0,null,null,null,null,1,0,0,0,0,0,0,null,0,0,0,0,null,null,null,null,null,null,null,null,null,null,null,null,null,null,null,1,null,null,0,0,0,0,0,null,0,null,null,0,null,null,null,null,null,1,0,0,null,null,null,1,0,0,null,null,null,null,null,null,null,null,null,null,null,null,null,null,null,null,null,null,null,null,null,null,null,null,null,null,1,0,0,0,null,null,0,0,0,0,null,null,0,0,0,null,0,0,null,0,null,null,0,0,0,null,null,0,0,null,null,null,null,1,0,0,0,null,0,null,0,null,null,1,0,0,0,0,null,null,0,0,null,null,0,0,0,null,0,null,null,null,null,1,null,null,1,0,0,0,0,null,null,null,null,1,0,0,0,null,0,null,0,null,null,null,null,1,0,0,null,null,null,null,1,0,null,null,null,null,null,null,null,0,null,null,null,0,null,null,0,null,0,null,0,null,null,0,0,null,null,0,0,null,0,0,null,0,0,null,null,null,0,null,null,null,null,null,null,null,null,null,1,0,0,null,null,null,1,0,null,null,1,null,1,0,0,0,null,0,0,null,null,null,1,0,0,0,0,null,null,null,0,0,0,0,null,null,null,0,0,0,null,0,0,null,null,null,null,null,null,1,0,0,null,0,null,null,1,0,null,null,1,0,0,null,null,null,1,0,null,0,0,0,null,null,null,0,null,null,null,null,1,0,null,null,1,null,null,0,0,null,null,1,0,null,null,1,0,0,null,null,1,0,0,null,null,null,null,1,0,0,null,null,0,null,0,null,null,0,0,null,0,null,null,null,null,1,0,null,null,null,null,1,0,0,0,0,0,0,0,null,null,null,0,null,0,null,null,null,1,0,0,0,null,0,null,null,1,null,null,null,null,1,0,null,0,0,0,null,0,null,null,0,null,null,null,null,null,null,1,0,null,0,0,0,0,0,0,0,null,0,null,null,null,null,1,0,0,0,0,0,0,null,null,1,0,0,null,null,null,null,1,0,null,0,null,0,0,null,null,0,0,null,null,0,null,null,null,1,0,null,0,0,null,0,null,0,0,0,0,null,0,null,null,null,null,null,1,0,0,0,0,0,0,null,0,null,null,null,null,null,1,0,0,null,0,null,null,null,0,0,null,null,0,null,0,0,null,0,null,null,0,null,0,0,null,null,0,0,null,0,null,null,0,null,0,null,null,0,null,0,null,0,null,0,0,null,null,null],"/Users/ajrkerr/Development/roo/test/test_roo.rb":[null,null,null,null,null,null,null,null,null,null,null,null,null,null,null,null,null,null,null,null,null,null,null,null,1,null,1,null,1,1,1,1,1,1,null,1,null,null,null,null,null,null,null,1,1,null,1,0,null,0,null,0,null,0,null,0,null,null,null,null,null,null,1,0,0,0,null,0,0,null,null,0,null,null,0,0,0,0,0,null,0,null,null,0,null,null,null,null,null,null,null,null,null,null,1,0,null,0,0,null,0,0,0,null,0,0,0,null,null,null,1,0,0,0,0,0,0,0,0,null,null,null,null,1,0,0,0,0,0,0,0,null,null,null,null,1,0,null,null,0,0,0,0,0,0,0,0,0,0,0,0,0,0,0,null,0,0,0,0,0,0,0,0,0,0,0,0,0,0,null,null,null,null,1,0,0,null,null,null,1,0,0,0,0,0,0,0,0,0,0,0,0,0,0,0,null,null,null,1,0,0,null,null,null,1,0,0,0,0,null,null,null,1,0,0,0,0,0,0,0,0,0,0,0,null,0,0,0,0,null,0,null,null,null,1,0,0,null,null,null,1,0,0,0,0,0,0,0,null,null,null,1,0,0,0,0,0,0,0,null,null,null,1,0,0,0,0,0,0,0,0,0,0,0,0,0,0,0,0,0,null,null,0,0,0,null,null,0,0,0,null,null,0,0,0,null,null,0,0,0,null,null,0,0,0,0,null,0,0,0,null,null,null,null,1,0,0,0,0,0,0,0,0,0,0,0,null,null,null,null,0,null,null,0,0,0,0,0,0,null,null,null,1,0,0,0,0,0,0,0,0,null,0,0,null,null,null,null,0,0,null,null,null,null,null,null,null,null,null,null,null,null,null,null,null,0,null,null,null,null,1,0,0,0,0,0,0,0,0,0,null,null,null,0,null,null,null,null,null,null,null,null,null,0,null,null,0,0,0,0,0,0,null,null,null,null,1,0,0,0,null,null,null,1,0,0,0,0,0,0,null,0,0,0,0,0,null,0,0,0,0,0,null,null,null,1,0,0,0,0,0,0,0,0,null,null,null,1,0,0,0,0,0,0,null,null,null,null,1,0,0,0,0,null,0,null,null,null,null,1,0,0,0,0,null,null,null,1,0,null,0,0,0,null,null,null,null,1,0,0,0,0,0,0,0,0,0,0,0,null,0,0,0,0,0,0,0,0,0,0,0,0,0,0,0,0,0,0,0,0,0,0,0,0,0,0,0,0,0,null,null,null,1,0,0,null,null,null,null,null,null,null,null,null,null,null,null,1,0,null,null,null,null,null,null,0,0,0,0,0,0,0,0,null,null,null,null,null,null,null,1,0,null,null,0,0,0,null,0,0,null,0,null,null,null,null,1,0,0,0,0,0,0,0,0,0,0,0,0,0,0,0,0,0,0,0,0,0,0,0,0,0,0,0,0,0,0,0,0,null,null,null,1,0,0,0,0,0,0,0,0,0,0,0,0,0,0,0,0,0,0,0,0,0,0,0,0,0,0,0,0,0,0,0,0,0,0,0,0,0,0,null,null,null,null,null,1,0,0,0,0,0,null,null,null,null,1,0,null,null,0,0,0,0,null,null,0,0,0,null,0,null,null,null,null,1,0,0,0,0,0,null,0,null,0,0,0,null,null,null,1,0,0,0,0,0,0,0,0,0,0,null,null,null,1,0,null,null,0,null,0,null,null,null,0,null,null,null,null,null,null,null,null,null,null,null,null,null,null,null,0,null,null,0,null,null,0,null,0,null,null,null,null,0,null,null,null,null,null,null,null,null,null,null,null,null,null,null,null,0,null,null,0,null,null,null,null,0,null,null,null,null,null,null,null,null,null,null,null,null,null,null,null,null,null,null,null,null,0,null,null,null,null,null,null,1,0,0,0,0,0,0,0,0,null,null,null,null,1,0,0,0,0,null,null,null,1,0,null,null,0,0,0,null,null,null,null,null,1,0,0,null,0,0,0,0,0,0,0,null,null,null,null,null,1,0,0,0,0,0,null,null,null,null,null,1,0,0,null,null,null,0,null,null,null,0,null,null,null,0,0,0,0,0,0,0,0,null,null,null,1,0,0,0,0,null,null,null,1,0,null,0,null,0,null,0,null,0,null,null,null,1,0,null,null,null,null,null,null,null,null,null,null,null,null,null,null,null,null,null,null,null,null,null,null,null,null,null,null,null,0,0,0,0,0,0,null,0,null,null,null,null,null,null,null,1,0,0,0,0,null,null,null,1,0,0,0,0,0,0,0,0,0,0,0,0,0,0,0,0,0,0,0,0,0,0,0,0,0,0,null,null,null,1,0,0,0,null,null,0,0,0,null,null,0,0,0,null,null,0,null,null,null,null,null,null,null,1,null,0,0,0,0,0,0,null,null,null,1,null,0,0,0,0,0,0,0,0,0,0,0,null,null,null,1,0,0,0,0,0,0,0,0,0,null,null,null,1,0,0,null,null,null,1,0,0,null,null,null,null,null,null,null,null,null,null,null,0,null,null,0,0,0,0,0,null,null,null,null,1,0,0,0,0,0,0,0,null,null,null,1,0,0,0,0,0,0,null,null,null,null,null,null,1,0,0,0,0,0,0,null,null,null,null,null,1,0,0,0,0,0,0,0,null,null,null,null,null,1,0,0,null,0,null,null,null,null,null,null,1,0,0,0,0,null,null,null,null,0,null,null,null,0,null,null,1,0,0,0,0,0,0,0,null,0,0,0,0,0,0,0,0,null,null,null,null,0,null,null,null,null,null,0,0,null,null,0,null,null,null,null,1,0,0,0,0,0,null,null,null,1,0,0,0,null,0,null,0,0,0,null,0,0,0,null,null,null,1,0,0,0,null,0,0,0,null,0,0,0,null,null,null,1,0,0,0,0,null,null,0,0,0,null,null,null,0,0,0,0,null,null,0,0,0,null,null,null,0,0,0,0,null,null,0,0,0,null,null,null,null,null,1,0,null,null,null,null,null,null,0,0,null,null,0,0,null,null,0,0,0,null,0,0,null,null,0,0,0,null,0,0,null,null,null,null,1,0,0,null,null,null,1,0,0,0,0,0,0,0,0,0,0,null,0,null,null,null,1,null,null,0,null,null,0,0,0,0,0,0,0,null,null,null,1,0,0,0,0,0,0,0,null,0,0,0,0,0,null,null,0,0,0,0,0,0,0,0,0,0,0,0,0,null,null,null,1,0,0,0,0,0,0,0,0,0,0,0,0,0,0,0,0,0,0,0,0,0,0,0,0,0,null,null,null,1,0,0,0,0,0,0,null,null,null,null,1,0,0,0,0,null,0,0,null,null,null,null,1,0,0,0,0,null,null,null,1,null,null,null,null,null,0,null,0,0,0,null,null,0,0,0,null,null,0,0,0,null,null,0,0,0,null,null,0,0,0,null,null,0,0,0,null,null,0,0,0,null,null,0,0,0,null,null,0,0,0,null,null,0,0,0,null,null,0,0,0,null,null,null,null,null,null,1,0,0,0,0,null,null,null,null,null,1,null,0,0,0,0,0,0,0,0,0,0,0,0,null,null,null,1,null,null,0,0,0,0,0,0,0,0,0,0,0,0,0,0,null,null,null,1,0,0,0,null,null,null,null,1,0,0,0,null,null,null,1,0,0,0,null,null,null,null,null,null,1,0,0,null,null,null,null,0,null,0,0,null,null,0,null,null,null,null,null,1,0,0,0,null,0,0,0,null,null,null,1,0,0,0,null,null,null,null,1,0,0,0,null,null,null,null,1,0,0,0,0,0,0,0,null,null,0,null,0,null,null,null,null,null,null,1,null,0,0,0,null,0,0,0,0,0,0,0,0,0,0,null,null,null,null,null,null,null,1,0,null,0,0,null,0,0,null,0,0,null,0,0,null,0,0,null,0,0,null,0,0,0,null,0,0,0,0,null,null,null,1,0,null,0,0,0,null,null,null,null,1,0,null,null,null,null,null,0,null,null,null,1,0,0,0,0,null,0,0,null,0,0,null,0,0,null,0,0,null,0,0,null,0,0,0,null,0,0,0,0,null,0,0,0,null,null,null,null,null,null,null,0,null,null,null,1,1,0,0,null,null,null,0,null,null,null,1,0,0,null,null,null,0,null,null,null,1,0,0,null,null,null,0,null,null,null,1,0,0,null,null,null,0,null,null,null,1,0,0,null,null,null,0,null,null,null,null,null,null,null,null,null,null,null,null,null,1,null,0,null,null,null,null,null,null,null,null,null,null,null,null,null,null,null,null,null,null,0,0,0,0,null,null,null,null,null,null,1,null,0,0,0,0,null,0,null,null,null,null,null,null,1,null,0,0,0,0,null,0,null,null,null,null,null,null,1,null,0,0,0,0,null,0,null,null,null,null,1,0,0,0,null,0,0,0,null,null,null,null,null,1,0,null,null,null,null,null,null,null,0,0,0,0,0,null,null,null,null,0,null,null,null,null,null,null,null,null,null,null,null,null,null,null,null,null,null,null,null,null,null,null,null,null,null,null,null,null,null,null,null,null,null,null,null,null,null,null,null,null,null,null,null,null,1,null,0,0,0,0,null,null,null,1,0,0,0,0,null,0,0,0,0,null,0,0,0,null,null,null,1,null,0,0,0,0,0,null,0,0,null,null,null,1,null,0,0,0,0,null,null,null,1,null,0,0,null,null,null,0,null,0,0,null,null,null,null,null,null,null,1,1,null,1,0,0,null,0,null,0,0,0,0,0,null,0,null,null,null,0,null,0,0,null,0,0,0,0,0,0,0,0,0,0,null,0,null,null,null,null,1,0,0,0,0,0,0,0,0,0,0,0,0,null,null,null,null,null,null,null,null,null,null,null,null,null,null,null,null,null,null,null,1,0,0,0,null,null,null,1,0,0,0,0,null,null,0,0,0,null,null,0,0,0,null,null,null,null,null,1,0,null,null,0,0,0,0,0,0,0,0,null,null,null,null,null,null,null,null,null,null,null,null,null,null,null,null,null,null,null,null,null,null,null,null,null,null,null,null,null,null,null,null,null,null,null,null,null,null,null,null,null,null,null,null,null,null,null,1,0,0,0,0,0,0,null,0,0,0,null,0,0,null,0,null,null,null,null,null,null,null,null,null,null,null,null,null,null,null,null,null,null,null,null,null,null,null,null,null,null,null,null,null,null,null,null,null,null,null,null,null,null,null,null,null,null,null,null,null,null,null,null,null,null,null,null,null,null,null,null,null,null,null,null,null,null,null,null,null,null,null,null,null,null,null,null,null,null,null,null,null,null,null,null,null,1,0,0,null,0,0,0,null,null,1,0,0,null,null,null,null]},"timestamp":1392350548}}
